{
  "cities": [
    "Delhi",
    "Noida",
    "Gurugram",
    "Faridabad",
    "Ghaziabad",
    "Mumbai",
    "Pune",
    "Nagpur",
    "Bengaluru",
    "Chennai",
    "Hyderabad",
    "Kolkata",
    "Ahmedabad",
    "Surat",
    "Jaipur",
    "Jodhpur",
    "Lucknow",
    "Kanpur",
    "Varanasi",
    "Agra",
    "Patna",
    "Bhopal",
    "Indore",
    "Chandigarh",
    "Ludhiana",
    "Amritsar",
    "Visakhapatnam",
    "Vijayawada",
    "Kochi",
    "Thiruvananthapuram",
    "Coimbatore",
    "Madurai",
    "Dehradun",
    "Ranchi",
    "Bhubaneswar",
    "Guwahati"
  ],
  "city_encoder": {
    "Delhi": 0,
    "Noida": 1,
    "Gurugram": 2,
    "Faridabad": 3,
    "Ghaziabad": 4,
    "Mumbai": 5,
    "Pune": 6,
    "Nagpur": 7,
    "Bengaluru": 8,
    "Chennai": 9,
    "Hyderabad": 10,
    "Kolkata": 11,
    "Ahmedabad": 12,
    "Surat": 13,
    "Jaipur": 14,
    "Jodhpur": 15,
    "Lucknow": 16,
    "Kanpur": 17,
    "Varanasi": 18,
    "Agra": 19,
    "Patna": 20,
    "Bhopal": 21,
    "Indore": 22,
    "Chandigarh": 23,
    "Ludhiana": 24,
    "Amritsar": 25,
    "Visakhapatnam": 26,
    "Vijayawada": 27,
    "Kochi": 28,
    "Thiruvananthapuram": 29,
    "Coimbatore": 30,
    "Madurai": 31,
    "Dehradun": 32,
    "Ranchi": 33,
    "Bhubaneswar": 34,
    "Guwahati": 35
  },
  "lookback_days": 30,
  "horizons_days": [
    1,
    2,
    3,
    7
  ],
  "total_samples": 34291,
  "train_samples": 23991,
  "val_samples": 5131,
  "test_samples": 5169,
  "mae_per_horizon": {
    "day1": 29.10919952392578,
    "day2": 30.979888916015625,
    "day3": 31.403711318969727,
    "day7": 33.45620346069336
  },
  "rmse_per_horizon": {
    "day1": 41.544145383254666,
    "day2": 44.06398074861215,
    "day3": 44.794159481262874,
    "day7": 47.0503439230921
  },
  "mape_per_horizon": {
    "day1": 24.381027221679688,
    "day2": 26.278194427490234,
    "day3": 26.479955673217773,
    "day7": 28.47378921508789
  },
  "cities_trained": [
    "Agra",
    "Ahmedabad",
    "Amritsar",
    "Bengaluru",
    "Bhopal",
    "Bhubaneswar",
    "Chandigarh",
    "Chennai",
    "Coimbatore",
    "Dehradun",
    "Delhi",
    "Faridabad",
    "Ghaziabad",
    "Gurugram",
    "Guwahati",
    "Hyderabad",
    "Indore",
    "Jaipur",
    "Jodhpur",
    "Kanpur",
    "Kochi",
    "Kolkata",
    "Lucknow",
    "Ludhiana",
    "Madurai",
    "Mumbai",
    "Nagpur",
    "Patna",
    "Pune",
    "Surat",
    "Thiruvananthapuram",
    "Varanasi",
    "Vijayawada",
    "Visakhapatnam"
  ],
  "cities_skipped": [
    "Noida",
    "Ranchi"
  ],
  "trained_at": "2026-05-11T15:04:22.451729+00:00",
  "scaler_feature_range": [
    0,
    1
  ]
}